citerus/__init__.py
citerus/citerus.py
citerus/citeruslogo.py
citerus/cryptodbreader.py
citerus-0.1.0.dist-info/LICENSE
citerus-0.1.0.dist-info/METADATA
citerus-0.1.0.dist-info/WHEEL
citerus-0.1.0.dist-info/entry_points.txt
citerus-0.1.0.dist-info/top_level.txt
citerus-0.1.0.dist-info/RECORD
