Metadata-Version: 2.1
Name: citerus
Version: 0.1.0
Summary: citerus retrieves your crypto citations
Home-page: https://github.com/matteocam/citerus
Author: Matteo Campanelli
Author-email: matteo.campanelli@gmail.com
License: MIT License
Keywords: citations,bibliography,latex
Classifier: License :: OSI Approved :: MIT License
Classifier: Programming Language :: Python :: 3
License-File: LICENSE
Requires-Dist: textual >=0.45.0
Requires-Dist: rich >=13.7.0
Requires-Dist: GitPython >=3.1.41
Requires-Dist: pyperclip
